k_seq/__init__.py
k_seq/data/__init__.py
k_seq/data/count_file.py
k_seq/data/datasets.py
k_seq/data/filters.py
k_seq/data/grouper.py
k_seq/data/seq_data.py
k_seq/data/seq_data_analyzer.py
k_seq/data/simu.py
k_seq/data/transform.py
k_seq/data/visualization.py
k_seq/estimator/__init__.py
k_seq/estimator/_estimator.py
k_seq/estimator/bootstrap.py
k_seq/estimator/convergence.py
k_seq/estimator/least_squares.py
k_seq/estimator/least_squares_batch.py
k_seq/estimator/visualizer.py
k_seq/model/__init__.py
k_seq/model/count.py
k_seq/model/kinetic.py
k_seq/model/pool.py
k_seq/utility/__init__.py
k_seq/utility/file_tools.py
k_seq/utility/func_tools.py
k_seq/utility/plot_tools.py
todo_codes/__init__.py
todo_codes/bs_convergence_test.py
todo_codes/build_features.py
todo_codes/confidence_estimation.py
todo_codes/k_seq.py
todo_codes/k_seq_eval.py
todo_codes/k_seq_old.py
todo_codes/fitting/__init__.py
todo_codes/fitting/bootstrap.py
k_seq-0.4.2a0.dist-info/METADATA
k_seq-0.4.2a0.dist-info/WHEEL
k_seq-0.4.2a0.dist-info/top_level.txt
k_seq-0.4.2a0.dist-info/RECORD
