Metadata-Version: 2.1
Name: k-seq
Version: 0.4.2a0
Summary: Kinetic sequencing analysis by Chen lab at University of California, Santa Barbara
Home-page: https://github.com/ynshen/k-seq
Author: Yuning Shen
Author-email: ynshen23@gmail.com
License: UNKNOWN
Project-URL: Bug Reports, https://github.com/ynshen/k-seq/issues/
Project-URL: Source, https://github.com/ynshen/k-seq
Keywords: bioinformatics sequencing fitting
Platform: UNKNOWN
Classifier: License :: OSI Approved :: MIT License
Requires-Python: >=3.5
Requires-Dist: pandas
Requires-Dist: numpy
Requires-Dist: scipy
Requires-Dist: matplotlib
Requires-Dist: python-levenshtein
Requires-Dist: seaborn
Requires-Dist: doc-helper
Requires-Dist: seq-landscape
Requires-Dist: yutility
